MANIFEST.in
README.md
setup.py
./opentc/__init__.py
./opentc/core/__init__.py
./opentc/core/server.py
./opentc/core/setting.py
./opentc/core/training.py
./opentc/core/classifier/__init__.py
./opentc/core/classifier/bayes.py
./opentc/core/classifier/cnn.py
./opentc/core/classifier/cnn_text.py
./opentc/core/classifier/cnn_text_util.py
./opentc/core/classifier/svm.py
./opentc/core/dataset/__init__.py
./opentc/core/dataset/generic.py
./opentc/core/dataset/mrpolarity.py
./opentc/core/dataset/twenty_newsgroup.py
./opentc/core/tests/__init__.py
./opentc/core/tests/test_opentc.py
./opentc/core/tests/test_setup_loging.py
bin/opentc
bin/opentcd
config/logging.yml
config/opentc.yml
opentc.egg-info/PKG-INFO
opentc.egg-info/SOURCES.txt
opentc.egg-info/dependency_links.txt
opentc.egg-info/not-zip-safe
opentc.egg-info/requires.txt
opentc.egg-info/top_level.txt